{
  "branch": "HEAD",
  "commands": [
    {
      "command": [
        "git",
        "rev-parse",
        "--show-toplevel"
      ],
      "exitCode": 0,
      "observedAtUtc": "2026-07-19T14:32:28Z",
      "stderr": "",
      "stdout": "<HOME>/work/AsyncScene/AsyncScene\n"
    },
    {
      "command": [
        "git",
        "rev-parse",
        "--abbrev-ref",
        "HEAD"
      ],
      "exitCode": 0,
      "observedAtUtc": "2026-07-19T14:32:28Z",
      "stderr": "",
      "stdout": "HEAD\n"
    },
    {
      "command": [
        "git",
        "rev-parse",
        "HEAD"
      ],
      "exitCode": 0,
      "observedAtUtc": "2026-07-19T14:32:28Z",
      "stderr": "",
      "stdout": "397bd0c03e04ea22a71c5806e6f460c7432beaee\n"
    },
    {
      "command": [
        "git",
        "status",
        "--porcelain=v2",
        "--branch"
      ],
      "exitCode": 0,
      "observedAtUtc": "2026-07-19T14:32:28Z",
      "stderr": "",
      "stdout": "# branch.oid 397bd0c03e04ea22a71c5806e6f460c7432beaee\n# branch.head (detached)\n"
    },
    {
      "command": [
        "git",
        "log",
        "--oneline",
        "--decorate",
        "-n",
        "5"
      ],
      "exitCode": 0,
      "observedAtUtc": "2026-07-19T14:32:28Z",
      "stderr": "",
      "stdout": "397bd0c0 (HEAD, pull/236/merge) Merge cf465da8077cb173b421eef24c9cbd08cef3563d into 4a5e0f9d0eb6e63b0704ca996f1446152905e785\ncf465da8 (origin/infra/post-r2-repository-memory-closure-20260719) Fix protective archive ref\nfb829597 Correct memory closure archive identity\n045cafd0 Preserve durable memory policy in closure\n2e5486d8 Close post-R2 repository memory\n"
    },
    {
      "command": [
        "git",
        "worktree",
        "list",
        "--porcelain"
      ],
      "exitCode": 0,
      "observedAtUtc": "2026-07-19T14:32:28Z",
      "stderr": "",
      "stdout": "worktree <HOME>/work/AsyncScene/AsyncScene\nHEAD 397bd0c03e04ea22a71c5806e6f460c7432beaee\ndetached\n\n"
    },
    {
      "command": [
        "git",
        "remote",
        "-v"
      ],
      "exitCode": 0,
      "observedAtUtc": "2026-07-19T14:32:28Z",
      "stderr": "",
      "stdout": "origin\thttps://github.com/samuray-games/AsyncScene (fetch)\norigin\thttps://github.com/samuray-games/AsyncScene (push)\n"
    },
    {
      "command": [
        "git",
        "rev-parse",
        "origin/main"
      ],
      "exitCode": 0,
      "observedAtUtc": "2026-07-19T14:32:28Z",
      "stderr": "",
      "stdout": "4a5e0f9d0eb6e63b0704ca996f1446152905e785\n"
    }
  ],
  "cwd": "<HOME>/work/AsyncScene/AsyncScene",
  "head": "397bd0c03e04ea22a71c5806e6f460c7432beaee",
  "observedAtUtc": "2026-07-19T14:32:28Z",
  "refs": [
    "origin/main"
  ],
  "repositoryRoot": "<HOME>/work/AsyncScene/AsyncScene"
}
