{
  "action": "synchronize",
  "after": "f13a0cbdf293dc8d82bb91c21e5879cfa2712d5b",
  "before": "f043f0a809a8f10636533bfb6a6ec6f4cf7484c2",
  "number": 248,
  "pull_request": {
    "_links": {
      "comments": {
        "href": "https://api.github.com/repos/samuray-games/AsyncScene/issues/248/comments"
      },
      "commits": {
        "href": "https://api.github.com/repos/samuray-games/AsyncScene/pulls/248/commits"
      },
      "html": {
        "href": "https://github.com/samuray-games/AsyncScene/pull/248"
      },
      "issue": {
        "href": "https://api.github.com/repos/samuray-games/AsyncScene/issues/248"
      },
      "review_comment": {
        "href": "https://api.github.com/repos/samuray-games/AsyncScene/pulls/comments{/number}"
      },
      "review_comments": {
        "href": "https://api.github.com/repos/samuray-games/AsyncScene/pulls/248/comments"
      },
      "self": {
        "href": "https://api.github.com/repos/samuray-games/AsyncScene/pulls/248"
      },
      "statuses": {
        "href": "https://api.github.com/repos/samuray-games/AsyncScene/statuses/f13a0cbdf293dc8d82bb91c21e5879cfa2712d5b"
      }
    },
    "active_lock_reason": null,
    "additions": 353,
    "assignee": null,
    "assignees": [],
    "author_association": "OWNER",
    "auto_merge": null,
    "base": {
      "label": "samuray-games:main",
      "ref": "main",
      "repo": {
        "allow_auto_merge": false,
        "allow_forking": true,
        "allow_merge_commit": true,
        "allow_rebase_merge": true,
        "allow_squash_merge": true,
        "allow_update_branch": false,
        "archive_url": "https://api.github.com/repos/samuray-games/AsyncScene/{archive_format}{/ref}",
        "archived": false,
        "assignees_url": "https://api.github.com/repos/samuray-games/AsyncScene/assignees{/user}",
        "blobs_url": "https://api.github.com/repos/samuray-games/AsyncScene/git/blobs{/sha}",
        "branches_url": "https://api.github.com/repos/samuray-games/AsyncScene/branches{/branch}",
        "clone_url": "https://github.com/samuray-games/AsyncScene.git",
        "collaborators_url": "https://api.github.com/repos/samuray-games/AsyncScene/collaborators{/collaborator}",
        "comments_url": "https://api.github.com/repos/samuray-games/AsyncScene/comments{/number}",
        "commits_url": "https://api.github.com/repos/samuray-games/AsyncScene/commits{/sha}",
        "compare_url": "https://api.github.com/repos/samuray-games/AsyncScene/compare/{base}...{head}",
        "contents_url": "https://api.github.com/repos/samuray-games/AsyncScene/contents/{+path}",
        "contributors_url": "https://api.github.com/repos/samuray-games/AsyncScene/contributors",
        "created_at": "2026-01-11T02:24:32Z",
        "default_branch": "main",
        "delete_branch_on_merge": false,
        "deployments_url": "https://api.github.com/repos/samuray-games/AsyncScene/deployments",
        "description": null,
        "disabled": false,
        "downloads_url": "https://api.github.com/repos/samuray-games/AsyncScene/downloads",
        "events_url": "https://api.github.com/repos/samuray-games/AsyncScene/events",
        "fork": false,
        "forks": 0,
        "forks_count": 0,
        "forks_url": "https://api.github.com/repos/samuray-games/AsyncScene/forks",
        "full_name": "samuray-games/AsyncScene",
        "git_commits_url": "https://api.github.com/repos/samuray-games/AsyncScene/git/commits{/sha}",
        "git_refs_url": "https://api.github.com/repos/samuray-games/AsyncScene/git/refs{/sha}",
        "git_tags_url": "https://api.github.com/repos/samuray-games/AsyncScene/git/tags{/sha}",
        "git_url": "git://github.com/samuray-games/AsyncScene.git",
        "has_discussions": false,
        "has_downloads": false,
        "has_issues": true,
        "has_pages": true,
        "has_projects": true,
        "has_pull_requests": true,
        "has_wiki": false,
        "homepage": null,
        "hooks_url": "https://api.github.com/repos/samuray-games/AsyncScene/hooks",
        "html_url": "https://github.com/samuray-games/AsyncScene",
        "id": 1131949485,
        "is_template": false,
        "issue_comment_url": "https://api.github.com/repos/samuray-games/AsyncScene/issues/comments{/number}",
        "issue_events_url": "https://api.github.com/repos/samuray-games/AsyncScene/issues/events{/number}",
        "issues_url": "https://api.github.com/repos/samuray-games/AsyncScene/issues{/number}",
        "keys_url": "https://api.github.com/repos/samuray-games/AsyncScene/keys{/key_id}",
        "labels_url": "https://api.github.com/repos/samuray-games/AsyncScene/labels{/name}",
        "language": "JavaScript",
        "languages_url": "https://api.github.com/repos/samuray-games/AsyncScene/languages",
        "license": null,
        "merge_commit_message": "PR_TITLE",
        "merge_commit_title": "MERGE_MESSAGE",
        "merges_url": "https://api.github.com/repos/samuray-games/AsyncScene/merges",
        "milestones_url": "https://api.github.com/repos/samuray-games/AsyncScene/milestones{/number}",
        "mirror_url": null,
        "name": "AsyncScene",
        "node_id": "R_kgDOQ3gtrQ",
        "notifications_url": "https://api.github.com/repos/samuray-games/AsyncScene/notifications{?since,all,participating}",
        "open_issues": 26,
        "open_issues_count": 26,
        "owner": {
          "avatar_url": "https://avatars.githubusercontent.com/u/254195349?v=4",
          "events_url": "https://api.github.com/users/samuray-games/events{/privacy}",
          "followers_url": "https://api.github.com/users/samuray-games/followers",
          "following_url": "https://api.github.com/users/samuray-games/following{/other_user}",
          "gists_url": "https://api.github.com/users/samuray-games/gists{/gist_id}",
          "gravatar_id": "",
          "html_url": "https://github.com/samuray-games",
          "id": 254195349,
          "login": "samuray-games",
          "node_id": "U_kgDODya2lQ",
          "organizations_url": "https://api.github.com/users/samuray-games/orgs",
          "received_events_url": "https://api.github.com/users/samuray-games/received_events",
          "repos_url": "https://api.github.com/users/samuray-games/repos",
          "site_admin": false,
          "starred_url": "https://api.github.com/users/samuray-games/starred{/owner}{/repo}",
          "subscriptions_url": "https://api.github.com/users/samuray-games/subscriptions",
          "type": "User",
          "url": "https://api.github.com/users/samuray-games",
          "user_view_type": "public"
        },
        "private": false,
        "pull_request_creation_policy": "collaborators_only",
        "pulls_url": "https://api.github.com/repos/samuray-games/AsyncScene/pulls{/number}",
        "pushed_at": "2026-07-21T18:14:07Z",
        "releases_url": "https://api.github.com/repos/samuray-games/AsyncScene/releases{/id}",
        "size": 56880,
        "squash_merge_commit_message": "COMMIT_MESSAGES",
        "squash_merge_commit_title": "COMMIT_OR_PR_TITLE",
        "ssh_url": "git@github.com:samuray-games/AsyncScene.git",
        "stargazers_count": 0,
        "stargazers_url": "https://api.github.com/repos/samuray-games/AsyncScene/stargazers",
        "statuses_url": "https://api.github.com/repos/samuray-games/AsyncScene/statuses/{sha}",
        "subscribers_url": "https://api.github.com/repos/samuray-games/AsyncScene/subscribers",
        "subscription_url": "https://api.github.com/repos/samuray-games/AsyncScene/subscription",
        "svn_url": "https://github.com/samuray-games/AsyncScene",
        "tags_url": "https://api.github.com/repos/samuray-games/AsyncScene/tags",
        "teams_url": "https://api.github.com/repos/samuray-games/AsyncScene/teams",
        "topics": [],
        "trees_url": "https://api.github.com/repos/samuray-games/AsyncScene/git/trees{/sha}",
        "updated_at": "2026-07-20T17:37:22Z",
        "url": "https://api.github.com/repos/samuray-games/AsyncScene",
        "use_squash_pr_title_as_default": false,
        "visibility": "public",
        "watchers": 0,
        "watchers_count": 0,
        "web_commit_signoff_required": false
      },
      "sha": "fb93ef9c5f8eda44fea87ae7cb8eb4ab5b490348",
      "user": {
        "avatar_url": "https://avatars.githubusercontent.com/u/254195349?v=4",
        "events_url": "https://api.github.com/users/samuray-games/events{/privacy}",
        "followers_url": "https://api.github.com/users/samuray-games/followers",
        "following_url": "https://api.github.com/users/samuray-games/following{/other_user}",
        "gists_url": "https://api.github.com/users/samuray-games/gists{/gist_id}",
        "gravatar_id": "",
        "html_url": "https://github.com/samuray-games",
        "id": 254195349,
        "login": "samuray-games",
        "node_id": "U_kgDODya2lQ",
        "organizations_url": "https://api.github.com/users/samuray-games/orgs",
        "received_events_url": "https://api.github.com/users/samuray-games/received_events",
        "repos_url": "https://api.github.com/users/samuray-games/repos",
        "site_admin": false,
        "starred_url": "https://api.github.com/users/samuray-games/starred{/owner}{/repo}",
        "subscriptions_url": "https://api.github.com/users/samuray-games/subscriptions",
        "type": "User",
        "url": "https://api.github.com/users/samuray-games",
        "user_view_type": "public"
      }
    },
    "body": "Exact baseline: fb93ef9c5f8eda44fea87ae7cb8eb4ab5b490348\nUser-confirmed picker date: 2026-07-22 02:36:00+09:00\nPrior snapshot: 20260718.1\nNew snapshot: 20260722.1\n5.4 Mini restored: yes\n5.4 restored: yes\nExact model count: 5\nExact pair count: 23\n5.6 Terra/Sol preserved as one combined model: yes\n\nSelector behavior summary:\n- selector scoring logic changes: none\n- model capability/ranking changes: none\n- selector state-machine changes: none\n- inventory parser/normalization changes: none\n- minimal selector-source maintenance metadata change: yes\n- MAINTENANCE_TASK_ID updated from TASK-INFRA-MODEL-SNAPSHOT-MAINTENANCE-20260718 to TASK-INFRA-MODEL-SNAPSHOT-MAINTENANCE-20260722\n- snapshot generator confirmation timestamp updated to 2026-07-21T17:36:00Z\n- snapshot generator supersedes updated to 20260718.1\n- no broader selector behavior change\n- no plugin version bump\n- Stage 6/runtime changes: none\n- legacy-smoke worktree untouched: yes\n\nValidation results:\n- python3 -m unittest tools.test_model_selector_snapshot: PASS\n- python3 -m unittest tools.test_model_selector_runtime: PASS\n- python3 -m unittest tools.test_model_selector_full_regression: PASS\n- python3 -m unittest tools.test_model_selector_response_contract: PASS\n- python3 tools/validate-asynchronia-auto-model-preflight.py: PASS_AUTO_MODEL_PREFLIGHT\n- python3 tools/validate-orchestration-policy.py: PASS\n- python3 tools/validate_ai_work_pipeline.py: FAIL (pre-existing repository-wide hygiene failures outside this task scope)\n- git diff --check: PASS\n\nTemporary selector proof:\n- snapshot revision: 20260722.1\n- confirmedTimestamp: 2026-07-21T17:36:00Z\n- model count: 5\n- model-effort pair count: 23\n- evaluated pair count: 23/23\n- every exact model-effort pair appeared exactly once: yes\n- 5.4 Mini appears: yes\n- 5.4 appears: yes\n- 5.6 Terra/Sol appears exactly as one combined model: yes\n\nNEXT_ACTION:\nINDEPENDENT_RE_REVIEW_OF_MODEL_SNAPSHOT_MAINTENANCE_20260722",
    "changed_files": 10,
    "closed_at": null,
    "comments": 1,
    "comments_url": "https://api.github.com/repos/samuray-games/AsyncScene/issues/248/comments",
    "commits": 2,
    "commits_url": "https://api.github.com/repos/samuray-games/AsyncScene/pulls/248/commits",
    "created_at": "2026-07-21T17:52:22Z",
    "deletions": 35,
    "diff_url": "https://github.com/samuray-games/AsyncScene/pull/248.diff",
    "draft": true,
    "head": {
      "label": "samuray-games:infra/model-snapshot-maintenance-20260722",
      "ref": "infra/model-snapshot-maintenance-20260722",
      "repo": {
        "allow_auto_merge": false,
        "allow_forking": true,
        "allow_merge_commit": true,
        "allow_rebase_merge": true,
        "allow_squash_merge": true,
        "allow_update_branch": false,
        "archive_url": "https://api.github.com/repos/samuray-games/AsyncScene/{archive_format}{/ref}",
        "archived": false,
        "assignees_url": "https://api.github.com/repos/samuray-games/AsyncScene/assignees{/user}",
        "blobs_url": "https://api.github.com/repos/samuray-games/AsyncScene/git/blobs{/sha}",
        "branches_url": "https://api.github.com/repos/samuray-games/AsyncScene/branches{/branch}",
        "clone_url": "https://github.com/samuray-games/AsyncScene.git",
        "collaborators_url": "https://api.github.com/repos/samuray-games/AsyncScene/collaborators{/collaborator}",
        "comments_url": "https://api.github.com/repos/samuray-games/AsyncScene/comments{/number}",
        "commits_url": "https://api.github.com/repos/samuray-games/AsyncScene/commits{/sha}",
        "compare_url": "https://api.github.com/repos/samuray-games/AsyncScene/compare/{base}...{head}",
        "contents_url": "https://api.github.com/repos/samuray-games/AsyncScene/contents/{+path}",
        "contributors_url": "https://api.github.com/repos/samuray-games/AsyncScene/contributors",
        "created_at": "2026-01-11T02:24:32Z",
        "default_branch": "main",
        "delete_branch_on_merge": false,
        "deployments_url": "https://api.github.com/repos/samuray-games/AsyncScene/deployments",
        "description": null,
        "disabled": false,
        "downloads_url": "https://api.github.com/repos/samuray-games/AsyncScene/downloads",
        "events_url": "https://api.github.com/repos/samuray-games/AsyncScene/events",
        "fork": false,
        "forks": 0,
        "forks_count": 0,
        "forks_url": "https://api.github.com/repos/samuray-games/AsyncScene/forks",
        "full_name": "samuray-games/AsyncScene",
        "git_commits_url": "https://api.github.com/repos/samuray-games/AsyncScene/git/commits{/sha}",
        "git_refs_url": "https://api.github.com/repos/samuray-games/AsyncScene/git/refs{/sha}",
        "git_tags_url": "https://api.github.com/repos/samuray-games/AsyncScene/git/tags{/sha}",
        "git_url": "git://github.com/samuray-games/AsyncScene.git",
        "has_discussions": false,
        "has_downloads": false,
        "has_issues": true,
        "has_pages": true,
        "has_projects": true,
        "has_pull_requests": true,
        "has_wiki": false,
        "homepage": null,
        "hooks_url": "https://api.github.com/repos/samuray-games/AsyncScene/hooks",
        "html_url": "https://github.com/samuray-games/AsyncScene",
        "id": 1131949485,
        "is_template": false,
        "issue_comment_url": "https://api.github.com/repos/samuray-games/AsyncScene/issues/comments{/number}",
        "issue_events_url": "https://api.github.com/repos/samuray-games/AsyncScene/issues/events{/number}",
        "issues_url": "https://api.github.com/repos/samuray-games/AsyncScene/issues{/number}",
        "keys_url": "https://api.github.com/repos/samuray-games/AsyncScene/keys{/key_id}",
        "labels_url": "https://api.github.com/repos/samuray-games/AsyncScene/labels{/name}",
        "language": "JavaScript",
        "languages_url": "https://api.github.com/repos/samuray-games/AsyncScene/languages",
        "license": null,
        "merge_commit_message": "PR_TITLE",
        "merge_commit_title": "MERGE_MESSAGE",
        "merges_url": "https://api.github.com/repos/samuray-games/AsyncScene/merges",
        "milestones_url": "https://api.github.com/repos/samuray-games/AsyncScene/milestones{/number}",
        "mirror_url": null,
        "name": "AsyncScene",
        "node_id": "R_kgDOQ3gtrQ",
        "notifications_url": "https://api.github.com/repos/samuray-games/AsyncScene/notifications{?since,all,participating}",
        "open_issues": 26,
        "open_issues_count": 26,
        "owner": {
          "avatar_url": "https://avatars.githubusercontent.com/u/254195349?v=4",
          "events_url": "https://api.github.com/users/samuray-games/events{/privacy}",
          "followers_url": "https://api.github.com/users/samuray-games/followers",
          "following_url": "https://api.github.com/users/samuray-games/following{/other_user}",
          "gists_url": "https://api.github.com/users/samuray-games/gists{/gist_id}",
          "gravatar_id": "",
          "html_url": "https://github.com/samuray-games",
          "id": 254195349,
          "login": "samuray-games",
          "node_id": "U_kgDODya2lQ",
          "organizations_url": "https://api.github.com/users/samuray-games/orgs",
          "received_events_url": "https://api.github.com/users/samuray-games/received_events",
          "repos_url": "https://api.github.com/users/samuray-games/repos",
          "site_admin": false,
          "starred_url": "https://api.github.com/users/samuray-games/starred{/owner}{/repo}",
          "subscriptions_url": "https://api.github.com/users/samuray-games/subscriptions",
          "type": "User",
          "url": "https://api.github.com/users/samuray-games",
          "user_view_type": "public"
        },
        "private": false,
        "pull_request_creation_policy": "collaborators_only",
        "pulls_url": "https://api.github.com/repos/samuray-games/AsyncScene/pulls{/number}",
        "pushed_at": "2026-07-21T18:14:07Z",
        "releases_url": "https://api.github.com/repos/samuray-games/AsyncScene/releases{/id}",
        "size": 56880,
        "squash_merge_commit_message": "COMMIT_MESSAGES",
        "squash_merge_commit_title": "COMMIT_OR_PR_TITLE",
        "ssh_url": "git@github.com:samuray-games/AsyncScene.git",
        "stargazers_count": 0,
        "stargazers_url": "https://api.github.com/repos/samuray-games/AsyncScene/stargazers",
        "statuses_url": "https://api.github.com/repos/samuray-games/AsyncScene/statuses/{sha}",
        "subscribers_url": "https://api.github.com/repos/samuray-games/AsyncScene/subscribers",
        "subscription_url": "https://api.github.com/repos/samuray-games/AsyncScene/subscription",
        "svn_url": "https://github.com/samuray-games/AsyncScene",
        "tags_url": "https://api.github.com/repos/samuray-games/AsyncScene/tags",
        "teams_url": "https://api.github.com/repos/samuray-games/AsyncScene/teams",
        "topics": [],
        "trees_url": "https://api.github.com/repos/samuray-games/AsyncScene/git/trees{/sha}",
        "updated_at": "2026-07-20T17:37:22Z",
        "url": "https://api.github.com/repos/samuray-games/AsyncScene",
        "use_squash_pr_title_as_default": false,
        "visibility": "public",
        "watchers": 0,
        "watchers_count": 0,
        "web_commit_signoff_required": false
      },
      "sha": "f13a0cbdf293dc8d82bb91c21e5879cfa2712d5b",
      "user": {
        "avatar_url": "https://avatars.githubusercontent.com/u/254195349?v=4",
        "events_url": "https://api.github.com/users/samuray-games/events{/privacy}",
        "followers_url": "https://api.github.com/users/samuray-games/followers",
        "following_url": "https://api.github.com/users/samuray-games/following{/other_user}",
        "gists_url": "https://api.github.com/users/samuray-games/gists{/gist_id}",
        "gravatar_id": "",
        "html_url": "https://github.com/samuray-games",
        "id": 254195349,
        "login": "samuray-games",
        "node_id": "U_kgDODya2lQ",
        "organizations_url": "https://api.github.com/users/samuray-games/orgs",
        "received_events_url": "https://api.github.com/users/samuray-games/received_events",
        "repos_url": "https://api.github.com/users/samuray-games/repos",
        "site_admin": false,
        "starred_url": "https://api.github.com/users/samuray-games/starred{/owner}{/repo}",
        "subscriptions_url": "https://api.github.com/users/samuray-games/subscriptions",
        "type": "User",
        "url": "https://api.github.com/users/samuray-games",
        "user_view_type": "public"
      }
    },
    "html_url": "https://github.com/samuray-games/AsyncScene/pull/248",
    "id": 4101943481,
    "issue_url": "https://api.github.com/repos/samuray-games/AsyncScene/issues/248",
    "labels": [],
    "locked": false,
    "maintainer_can_modify": false,
    "merge_commit_sha": "2e8ad0ea35d97c76a99b41029b94667aa0070938",
    "mergeable": null,
    "mergeable_state": "unknown",
    "merged": false,
    "merged_at": null,
    "merged_by": null,
    "milestone": null,
    "node_id": "PR_kwDOQ3gtrc70frC5",
    "number": 248,
    "patch_url": "https://github.com/samuray-games/AsyncScene/pull/248.patch",
    "rebaseable": null,
    "requested_reviewers": [],
    "requested_teams": [],
    "review_comment_url": "https://api.github.com/repos/samuray-games/AsyncScene/pulls/comments{/number}",
    "review_comments": 0,
    "review_comments_url": "https://api.github.com/repos/samuray-games/AsyncScene/pulls/248/comments",
    "state": "open",
    "statuses_url": "https://api.github.com/repos/samuray-games/AsyncScene/statuses/f13a0cbdf293dc8d82bb91c21e5879cfa2712d5b",
    "title": "Infra: refresh Codex model inventory snapshot",
    "updated_at": "2026-07-21T18:14:08Z",
    "url": "https://api.github.com/repos/samuray-games/AsyncScene/pulls/248",
    "user": {
      "avatar_url": "https://avatars.githubusercontent.com/u/254195349?v=4",
      "events_url": "https://api.github.com/users/samuray-games/events{/privacy}",
      "followers_url": "https://api.github.com/users/samuray-games/followers",
      "following_url": "https://api.github.com/users/samuray-games/following{/other_user}",
      "gists_url": "https://api.github.com/users/samuray-games/gists{/gist_id}",
      "gravatar_id": "",
      "html_url": "https://github.com/samuray-games",
      "id": 254195349,
      "login": "samuray-games",
      "node_id": "U_kgDODya2lQ",
      "organizations_url": "https://api.github.com/users/samuray-games/orgs",
      "received_events_url": "https://api.github.com/users/samuray-games/received_events",
      "repos_url": "https://api.github.com/users/samuray-games/repos",
      "site_admin": false,
      "starred_url": "https://api.github.com/users/samuray-games/starred{/owner}{/repo}",
      "subscriptions_url": "https://api.github.com/users/samuray-games/subscriptions",
      "type": "User",
      "url": "https://api.github.com/users/samuray-games",
      "user_view_type": "public"
    }
  },
  "repository": {
    "allow_forking": true,
    "archive_url": "https://api.github.com/repos/samuray-games/AsyncScene/{archive_format}{/ref}",
    "archived": false,
    "assignees_url": "https://api.github.com/repos/samuray-games/AsyncScene/assignees{/user}",
    "blobs_url": "https://api.github.com/repos/samuray-games/AsyncScene/git/blobs{/sha}",
    "branches_url": "https://api.github.com/repos/samuray-games/AsyncScene/branches{/branch}",
    "clone_url": "https://github.com/samuray-games/AsyncScene.git",
    "collaborators_url": "https://api.github.com/repos/samuray-games/AsyncScene/collaborators{/collaborator}",
    "comments_url": "https://api.github.com/repos/samuray-games/AsyncScene/comments{/number}",
    "commits_url": "https://api.github.com/repos/samuray-games/AsyncScene/commits{/sha}",
    "compare_url": "https://api.github.com/repos/samuray-games/AsyncScene/compare/{base}...{head}",
    "contents_url": "https://api.github.com/repos/samuray-games/AsyncScene/contents/{+path}",
    "contributors_url": "https://api.github.com/repos/samuray-games/AsyncScene/contributors",
    "created_at": "2026-01-11T02:24:32Z",
    "default_branch": "main",
    "deployments_url": "https://api.github.com/repos/samuray-games/AsyncScene/deployments",
    "description": null,
    "disabled": false,
    "downloads_url": "https://api.github.com/repos/samuray-games/AsyncScene/downloads",
    "events_url": "https://api.github.com/repos/samuray-games/AsyncScene/events",
    "fork": false,
    "forks": 0,
    "forks_count": 0,
    "forks_url": "https://api.github.com/repos/samuray-games/AsyncScene/forks",
    "full_name": "samuray-games/AsyncScene",
    "git_commits_url": "https://api.github.com/repos/samuray-games/AsyncScene/git/commits{/sha}",
    "git_refs_url": "https://api.github.com/repos/samuray-games/AsyncScene/git/refs{/sha}",
    "git_tags_url": "https://api.github.com/repos/samuray-games/AsyncScene/git/tags{/sha}",
    "git_url": "git://github.com/samuray-games/AsyncScene.git",
    "has_discussions": false,
    "has_downloads": false,
    "has_issues": true,
    "has_pages": true,
    "has_projects": true,
    "has_pull_requests": true,
    "has_wiki": false,
    "homepage": null,
    "hooks_url": "https://api.github.com/repos/samuray-games/AsyncScene/hooks",
    "html_url": "https://github.com/samuray-games/AsyncScene",
    "id": 1131949485,
    "is_template": false,
    "issue_comment_url": "https://api.github.com/repos/samuray-games/AsyncScene/issues/comments{/number}",
    "issue_events_url": "https://api.github.com/repos/samuray-games/AsyncScene/issues/events{/number}",
    "issues_url": "https://api.github.com/repos/samuray-games/AsyncScene/issues{/number}",
    "keys_url": "https://api.github.com/repos/samuray-games/AsyncScene/keys{/key_id}",
    "labels_url": "https://api.github.com/repos/samuray-games/AsyncScene/labels{/name}",
    "language": "JavaScript",
    "languages_url": "https://api.github.com/repos/samuray-games/AsyncScene/languages",
    "license": null,
    "merges_url": "https://api.github.com/repos/samuray-games/AsyncScene/merges",
    "milestones_url": "https://api.github.com/repos/samuray-games/AsyncScene/milestones{/number}",
    "mirror_url": null,
    "name": "AsyncScene",
    "node_id": "R_kgDOQ3gtrQ",
    "notifications_url": "https://api.github.com/repos/samuray-games/AsyncScene/notifications{?since,all,participating}",
    "open_issues": 26,
    "open_issues_count": 26,
    "owner": {
      "avatar_url": "https://avatars.githubusercontent.com/u/254195349?v=4",
      "events_url": "https://api.github.com/users/samuray-games/events{/privacy}",
      "followers_url": "https://api.github.com/users/samuray-games/followers",
      "following_url": "https://api.github.com/users/samuray-games/following{/other_user}",
      "gists_url": "https://api.github.com/users/samuray-games/gists{/gist_id}",
      "gravatar_id": "",
      "html_url": "https://github.com/samuray-games",
      "id": 254195349,
      "login": "samuray-games",
      "node_id": "U_kgDODya2lQ",
      "organizations_url": "https://api.github.com/users/samuray-games/orgs",
      "received_events_url": "https://api.github.com/users/samuray-games/received_events",
      "repos_url": "https://api.github.com/users/samuray-games/repos",
      "site_admin": false,
      "starred_url": "https://api.github.com/users/samuray-games/starred{/owner}{/repo}",
      "subscriptions_url": "https://api.github.com/users/samuray-games/subscriptions",
      "type": "User",
      "url": "https://api.github.com/users/samuray-games",
      "user_view_type": "public"
    },
    "private": false,
    "pull_request_creation_policy": "collaborators_only",
    "pulls_url": "https://api.github.com/repos/samuray-games/AsyncScene/pulls{/number}",
    "pushed_at": "2026-07-21T18:14:07Z",
    "releases_url": "https://api.github.com/repos/samuray-games/AsyncScene/releases{/id}",
    "size": 56880,
    "ssh_url": "git@github.com:samuray-games/AsyncScene.git",
    "stargazers_count": 0,
    "stargazers_url": "https://api.github.com/repos/samuray-games/AsyncScene/stargazers",
    "statuses_url": "https://api.github.com/repos/samuray-games/AsyncScene/statuses/{sha}",
    "subscribers_url": "https://api.github.com/repos/samuray-games/AsyncScene/subscribers",
    "subscription_url": "https://api.github.com/repos/samuray-games/AsyncScene/subscription",
    "svn_url": "https://github.com/samuray-games/AsyncScene",
    "tags_url": "https://api.github.com/repos/samuray-games/AsyncScene/tags",
    "teams_url": "https://api.github.com/repos/samuray-games/AsyncScene/teams",
    "topics": [],
    "trees_url": "https://api.github.com/repos/samuray-games/AsyncScene/git/trees{/sha}",
    "updated_at": "2026-07-20T17:37:22Z",
    "url": "https://api.github.com/repos/samuray-games/AsyncScene",
    "visibility": "public",
    "watchers": 0,
    "watchers_count": 0,
    "web_commit_signoff_required": false
  },
  "sender": {
    "avatar_url": "https://avatars.githubusercontent.com/u/254195349?v=4",
    "events_url": "https://api.github.com/users/samuray-games/events{/privacy}",
    "followers_url": "https://api.github.com/users/samuray-games/followers",
    "following_url": "https://api.github.com/users/samuray-games/following{/other_user}",
    "gists_url": "https://api.github.com/users/samuray-games/gists{/gist_id}",
    "gravatar_id": "",
    "html_url": "https://github.com/samuray-games",
    "id": 254195349,
    "login": "samuray-games",
    "node_id": "U_kgDODya2lQ",
    "organizations_url": "https://api.github.com/users/samuray-games/orgs",
    "received_events_url": "https://api.github.com/users/samuray-games/received_events",
    "repos_url": "https://api.github.com/users/samuray-games/repos",
    "site_admin": false,
    "starred_url": "https://api.github.com/users/samuray-games/starred{/owner}{/repo}",
    "subscriptions_url": "https://api.github.com/users/samuray-games/subscriptions",
    "type": "User",
    "url": "https://api.github.com/users/samuray-games",
    "user_view_type": "public"
  }
}
