{
  "branch": "infra/model-snapshot-maintenance-20260718",
  "commands": [
    {
      "command": [
        "git",
        "rev-parse",
        "--show-toplevel"
      ],
      "exitCode": 0,
      "observedAtUtc": "2026-07-19T08:59:49Z",
      "stderr": "",
      "stdout": "<HOME>/work/AsyncScene/AsyncScene\n"
    },
    {
      "command": [
        "git",
        "rev-parse",
        "--abbrev-ref",
        "HEAD"
      ],
      "exitCode": 0,
      "observedAtUtc": "2026-07-19T08:59:49Z",
      "stderr": "",
      "stdout": "infra/model-snapshot-maintenance-20260718\n"
    },
    {
      "command": [
        "git",
        "rev-parse",
        "HEAD"
      ],
      "exitCode": 0,
      "observedAtUtc": "2026-07-19T08:59:49Z",
      "stderr": "",
      "stdout": "c15a9ebc6c6ce0a914ac1554a8b8044931be29b1\n"
    },
    {
      "command": [
        "git",
        "status",
        "--porcelain=v2",
        "--branch"
      ],
      "exitCode": 0,
      "observedAtUtc": "2026-07-19T08:59:49Z",
      "stderr": "",
      "stdout": "# branch.oid c15a9ebc6c6ce0a914ac1554a8b8044931be29b1\n# branch.head infra/model-snapshot-maintenance-20260718\n# branch.upstream origin/infra/model-snapshot-maintenance-20260718\n# branch.ab +0 -0\n"
    },
    {
      "command": [
        "git",
        "log",
        "--oneline",
        "--decorate",
        "-n",
        "5"
      ],
      "exitCode": 0,
      "observedAtUtc": "2026-07-19T08:59:49Z",
      "stderr": "",
      "stdout": "c15a9ebc (HEAD -> infra/model-snapshot-maintenance-20260718, origin/infra/model-snapshot-maintenance-20260718) Maintain Asynchronia model inventory snapshot\nf351ffd5 Revert \"Merge branch 'main' of https://github.com/samuray-games/AsyncScene into infra/bridge-control-plane-reset-20260716\" (#233)\n88b6b10d Merge branch 'main' of https://github.com/samuray-games/AsyncScene into infra/bridge-control-plane-reset-20260716\nf917370a R3: repair visible selector matrix relay contract (#232)\na2bd3f47 Synchronize memory after model-preflight repair (#229)\n"
    },
    {
      "command": [
        "git",
        "worktree",
        "list",
        "--porcelain"
      ],
      "exitCode": 0,
      "observedAtUtc": "2026-07-19T08:59:49Z",
      "stderr": "",
      "stdout": "worktree <HOME>/work/AsyncScene/AsyncScene\nHEAD c15a9ebc6c6ce0a914ac1554a8b8044931be29b1\nbranch refs/heads/infra/model-snapshot-maintenance-20260718\n\n"
    },
    {
      "command": [
        "git",
        "remote",
        "-v"
      ],
      "exitCode": 0,
      "observedAtUtc": "2026-07-19T08:59:49Z",
      "stderr": "",
      "stdout": "origin\thttps://github.com/samuray-games/AsyncScene (fetch)\norigin\thttps://github.com/samuray-games/AsyncScene (push)\n"
    },
    {
      "command": [
        "git",
        "rev-parse",
        "origin/main"
      ],
      "exitCode": 0,
      "observedAtUtc": "2026-07-19T08:59:49Z",
      "stderr": "",
      "stdout": "4a5e0f9d0eb6e63b0704ca996f1446152905e785\n"
    }
  ],
  "cwd": "<HOME>/work/AsyncScene/AsyncScene",
  "head": "c15a9ebc6c6ce0a914ac1554a8b8044931be29b1",
  "observedAtUtc": "2026-07-19T08:59:49Z",
  "refs": [
    "origin/main"
  ],
  "repositoryRoot": "<HOME>/work/AsyncScene/AsyncScene"
}
